adsocket_transport/__init__.py
adsocket_transport/exceptions.py
adsocket_transport/message.py
adsocket_transport/transport.py
adsocket_transport/utils.py
adsocket_transport/version.py
adsocket_transport/broker/__init__.py
adsocket_transport/broker/aio_redis.py
adsocket_transport/broker/redis.py
adsocket_transport-0.2.0.dist-info/LICENSE
adsocket_transport-0.2.0.dist-info/METADATA
adsocket_transport-0.2.0.dist-info/WHEEL
adsocket_transport-0.2.0.dist-info/top_level.txt
adsocket_transport-0.2.0.dist-info/zip-safe
adsocket_transport-0.2.0.dist-info/RECORD
