Metadata-Version: 2.1
Name: adsocket-transport
Version: 0.2.0
Summary: ADSocket transport library
Home-page: https://github.com/AwesomeDevelopersUG/adsocket-transport
Author: Awesome Developers UG
Author-email: support@awesomedevelopers.eu
Maintainer: Awesome Developers UG
Maintainer-email: support@awesomedevelopers.eu
License: MIT
Platform: any
Classifier: Programming Language :: Python :: 3.7
Classifier: Programming Language :: Python :: 3.8
Classifier: License :: OSI Approved :: MIT License
Classifier: Operating System :: OS Independent
Classifier: Development Status :: 4 - Beta
License-File: LICENSE
Requires-Dist: redis (>=3.2.1)
Provides-Extra: aioredis
Requires-Dist: aioredis (>=2.0.0) ; extra == 'aioredis'
